.gitignore
MANIFEST.in
README.md
setup.py
.github/workflows/main.yml
docs/Makefile
docs/make.bat
docs/requirements.txt
docs/source/about.rst
docs/source/conf.py
docs/source/index.rst
docs/source/installation.rst
docs/source/stillingerweber.rst
docs/source/tip4p.rst
docs/source/vashishta.rst
examples/Si.sw
examples/sw_si.py
examples/tip4p-2005_h2o.py
examples/vashishta_h2o.py
examples/vashishta_scale.py
genpot/__init__.py
genpot/forcefield.py
genpot/io.py
genpot/stillingerweber.py
genpot/tip4p.py
genpot/usc.py
genpot/vashishta.py
genpot.egg-info/PKG-INFO
genpot.egg-info/SOURCES.txt
genpot.egg-info/dependency_links.txt
genpot.egg-info/top_level.txt
genpot/data/header.sw
genpot/data/header.vashishta
genpot/param/__init__.py
genpot/param/sw/__init__.py
genpot/param/sw/si_stillinger_1985.py
genpot/param/tip4p/__init__.py
genpot/param/tip4p/h2o_jorgensen_1984.py
genpot/param/tip4p/tip4p-2005.py
genpot/param/tip4p/tip4p-ew.py
genpot/param/tip4p/tip4p-ice.py
genpot/param/vashishta/__init__.py
genpot/param/vashishta/h2o_20060921.py
genpot/param/vashishta/h2o_2007.py
genpot/param/vashishta/h2o_20081216.py
genpot/param/vashishta/h2o_20100415.py
genpot/param/vashishta/h2o_20101223.py
genpot/param/vashishta/h2o_20110114.py
genpot/param/vashishta/h2o_hafreager_2016.py
genpot/param/vashishta/h2o_wang_2007.py
genpot/param/vashishta/h2o_wang_2010.py
genpot/param/vashishta/lnp_branicio_2009.py
genpot/param/vashishta/sic_vashishta_2007.py
genpot/param/vashishta/sio2_vashishta_1990.py
genpot/param/vashishta/sio2_vashishta_1997.py
genpot/param/vashishta/sio2_vashishta_wang.py
genpot/param/vashishta/sioh_wang_2007.py