Metadata-Version: 2.1
Name: genpot
Version: 1.3.0
Summary: Generate potential files used by LAMMPS
Home-page: https://github.com/evenmn/generate-potential-files
Author: Even Marius Nordhagen
Author-email: evenmn@fys.uio.no
Classifier: Programming Language :: Python :: 3
Classifier: Operating System :: OS Independent
Requires-Python: >=3.6
